{
  "Subject": {
    "Id": "i465270",
    "Name": "Mary Hendry Crawford",
    "Gender": "Female",
    "DateOfBirth": "22/Mar/1912",
    "DateOfDeath": "1991"
  },
  "Parents": [
    {
      "Id": "i33792128",
      "Name": "John Crawford",
      "Gender": "Male",
      "DateOfBirth": "",
      "DateOfDeath": "before 1936",
      "RelationToSubject": "father"
    },
    {
      "Id": "i79368912",
      "Name": "Agnes Gibb Hendry",
      "Gender": "Female",
      "DateOfBirth": "",
      "DateOfDeath": "after 1936",
      "RelationToSubject": "mother"
    }
  ],
  "Siblings": [
    {
      "Id": "i465270",
      "Name": "Mary Hendry Crawford",
      "Gender": "Female",
      "DateOfBirth": "22/Mar/1912",
      "DateOfDeath": "1991",
      "RelationToSubject": "self",
      "ParentGroupIds": [
        [
          "i33792128",
          "i79368912"
        ]
      ]
    }
  ],
  "Spouses": [
    {
      "Id": "i90830540",
      "Name": "Roderick McKenzie McIver",
      "Gender": "Male",
      "DateOfBirth": "22/Oct/1910",
      "DateOfDeath": "1999",
      "RelationToSubject": "husband",
      "DateOfMarriage": "1/Jul/1936",
      "DateOfDivorce": ""
    }
  ],
  "Children": [
    {
      "Id": "i15052620",
      "Name": "X",
      "Gender": "Female",
      "DateOfBirth": "1940",
      "DateOfDeath": "",
      "RelationToSubject": "daughter",
      "ParentIds": [
        "i90830540",
        "i465270"
      ]
    }
  ]
}