{
  "Subject": {
    "Id": "i38140776",
    "Name": "Kenneth Mackay",
    "Gender": "Male",
    "DateOfBirth": "about 1877",
    "DateOfDeath": ""
  },
  "Parents": [
    {
      "Id": "i21362348",
      "Name": "Kenneth Mackay",
      "Gender": "Male",
      "DateOfBirth": "19/Jan/1817",
      "DateOfDeath": "21/Feb/1894",
      "RelationToSubject": "father"
    },
    {
      "Id": "i52409786",
      "Name": "Barbara Mackay",
      "Gender": "Female",
      "DateOfBirth": "bet' 1849 and 1854",
      "DateOfDeath": "",
      "RelationToSubject": "mother"
    }
  ],
  "Siblings": [
    {
      "Id": "i32622896",
      "Name": "Kenneth Mackay",
      "Gender": "Male",
      "DateOfBirth": "1870",
      "DateOfDeath": "29/Apr/1871",
      "RelationToSubject": "brother",
      "ParentGroupIds": [
        [
          "i21362348",
          "i52409786"
        ]
      ]
    },
    {
      "Id": "i46319502",
      "Name": "George Mackay",
      "Gender": "Male",
      "DateOfBirth": "about 1875",
      "DateOfDeath": "",
      "RelationToSubject": "brother",
      "ParentGroupIds": [
        [
          "i21362348",
          "i52409786"
        ]
      ]
    },
    {
      "Id": "i38140776",
      "Name": "Kenneth Mackay",
      "Gender": "Male",
      "DateOfBirth": "about 1877",
      "DateOfDeath": "",
      "RelationToSubject": "self",
      "ParentGroupIds": [
        [
          "i21362348",
          "i52409786"
        ]
      ]
    },
    {
      "Id": "i66349958",
      "Name": "David Mackay",
      "Gender": "Male",
      "DateOfBirth": "about 1879",
      "DateOfDeath": "",
      "RelationToSubject": "brother",
      "ParentGroupIds": [
        [
          "i21362348",
          "i52409786"
        ]
      ]
    },
    {
      "Id": "i5045152",
      "Name": "Thomas Mackay",
      "Gender": "Male",
      "DateOfBirth": "27/Jun/1882",
      "DateOfDeath": "9/Nov/1934",
      "RelationToSubject": "brother",
      "ParentGroupIds": [
        [
          "i21362348",
          "i52409786"
        ]
      ]
    },
    {
      "Id": "i54814674",
      "Name": "Bella Mackay",
      "Gender": "Male",
      "DateOfBirth": "about 1885",
      "DateOfDeath": "",
      "RelationToSubject": "brother",
      "ParentGroupIds": [
        [
          "i21362348",
          "i52409786"
        ]
      ]
    }
  ],
  "Spouses": [],
  "Children": []
}